{"name": "color-theme-calm-forest","docs": ["Color theme by Artur Hefczyc, created 2003-04-18."],"data": ["color-theme-calm-forest", {"background-color":"gray12", "background-mode":"dark", "border-color":"black", "cursor-color":"orange", "foreground-color":"green", "mouse-color":"yellow"}, {"help-highlight-face":"underline", "list-matching-lines-face":"bold", "senator-eldoc-use-color":true, "view-highlight-face":"highlight", "widget-mouse-face":"highlight"}, ["default", {"true":{"stipple":[null, "background", "gray12", "foreground", "green", "inverse-video", null, "box", null, "strike-through", null, "overline", null, "underline", null, "slant", "normal", "weight", "normal", "height", 98, "width", "normal", "family", "outline-courier new"]}}], ["Info-title-1-face", {"true":{"bold":[true, "weight", "bold", "family", "helv", "height", 1.728]}}], ["Info-title-2-face", {"true":{"bold":[true, "family", "helv", "weight", "bold", "height", 1.44]}}], ["Info-title-3-face", {"true":{"bold":[true, "weight", "bold", "family", "helv", "height", 1.2]}}], ["Info-title-4-face", {"true":{"bold":[true, "family", "helv", "weight", "bold"]}}], ["bold", {"true":{"bold":[true, "weight", "bold"]}}], ["bold-italic", {"true":{"italic":[true, "slant", "italic", "weight", "bold"]}}], ["border", {"true":{"background":["black"]}}], ["comint-highlight-input", {"true":{"bold":[true, "weight", "bold"]}}], ["comint-highlight-prompt", {"true":{"foreground":["cyan"]}}], ["cparen-around-andor-face", {"true":{"bold":[true, "foreground", "maroon", "weight", "bold"]}}], ["cparen-around-begin-face", {"true":{"foreground":["maroon"]}}], ["cparen-around-conditional-face", {"true":{"bold":[true, "foreground", "RoyalBlue", "weight", "bold"]}}], ["cparen-around-define-face", {"true":{"bold":[true, "foreground", "Blue", "weight", "bold"]}}], ["cparen-around-lambda-face", {"true":{"foreground":["LightSeaGreen"]}}], ["cparen-around-letdo-face", {"true":{"bold":[true, "foreground", "LightSeaGreen", "weight", "bold"]}}], ["cparen-around-quote-face", {"true":{"foreground":["SaddleBrown"]}}], ["cparen-around-set!-face", {"true":{"foreground":["OrangeRed"]}}], ["cparen-around-syntax-rules-face", {"true":{"foreground":["Magenta"]}}], ["cparen-around-vector-face", {"true":{"foreground":["chocolate"]}}], ["cparen-binding-face", {"true":{"foreground":["ForestGreen"]}}], ["cparen-binding-list-face", {"true":{"bold":[true, "foreground", "ForestGreen", "weight", "bold"]}}], ["cparen-conditional-clause-face", {"true":{"foreground":["RoyalBlue"]}}], ["cparen-normal-paren-face", {"true":{"foreground":["grey50"]}}], ["cursor", {"true":{"background":["orange"]}}], ["custom-button-face", {"true":{"background":["lightgrey", "foreground", "black", "box", {"line-width":2, "style":"released-button"}]}}], ["custom-button-pressed-face", {"true":{"background":["lightgrey", "foreground", "black", "box", {"line-width":2, "style":"pressed-button"}]}}], ["custom-changed-face", {"true":{"background":["blue", "foreground", "white"]}}], ["custom-comment-face", {"true":{"background":["dim gray"]}}], ["custom-comment-tag-face", {"true":{"foreground":["gray80"]}}], ["custom-documentation-face", {"true":{"null":null}}], ["custom-face-tag-face", {"true":{"bold":[true, "family", "helv", "weight", "bold", "height", 1.2]}}], ["custom-group-tag-face", {"true":{"bold":[true, "foreground", "light blue", "weight", "bold", "height", 1.2]}}], ["custom-group-tag-face-1", {"true":{"bold":[true, "family", "helv", "foreground", "pink", "weight", "bold", "height", 1.2]}}], ["custom-invalid-face", {"true":{"background":["red", "foreground", "yellow"]}}], ["custom-modified-face", {"true":{"background":["blue", "foreground", "white"]}}], ["custom-rogue-face", {"true":{"background":["black", "foreground", "pink"]}}], ["custom-saved-face", {"true":{"underline":[true]}}], ["custom-set-face", {"true":{"background":["white", "foreground", "blue"]}}], ["custom-state-face", {"true":{"foreground":["lime green"]}}], ["custom-variable-button-face", {"true":{"bold":[true, "underline", true, "weight", "bold"]}}], ["custom-variable-tag-face", {"true":{"bold":[true, "family", "helv", "foreground", "light blue", "weight", "bold", "height", 1.2]}}], ["eieio-custom-slot-tag-face", {"true":{"foreground":["light blue"]}}], ["extra-whitespace-face", {"true":{"background":["pale green"]}}], ["fixed-pitch", {"true":{"family":["courier"]}}], ["font-latex-bold-face", {"true":{"bold":[true, "foreground", "OliveDrab", "weight", "bold"]}}], ["font-latex-italic-face", {"true":{"italic":[true, "foreground", "OliveDrab", "slant", "italic"]}}], ["font-latex-math-face", {"true":{"foreground":["burlywood"]}}], ["font-latex-sedate-face", {"true":{"foreground":["LightGray"]}}], ["font-latex-string-face", {"true":{"foreground":["RosyBrown"]}}], ["font-latex-warning-face", {"true":{"bold":[true, "foreground", "Red", "weight", "bold"]}}], ["font-lock-builtin-face", {"true":{"foreground":["LightSteelBlue"]}}], ["font-lock-comment-face", {"true":{"foreground":["chocolate1"]}}], ["font-lock-constant-face", {"true":{"foreground":["Aquamarine"]}}], ["font-lock-doc-face", {"true":{"foreground":["LightSalmon"]}}], ["font-lock-function-name-face", {"true":{"foreground":["LightSkyBlue"]}}], ["font-lock-keyword-face", {"true":{"foreground":["Cyan"]}}], ["font-lock-string-face", {"true":{"foreground":["LightSalmon"]}}], ["font-lock-type-face", {"true":{"foreground":["PaleGreen"]}}], ["font-lock-variable-name-face", {"true":{"foreground":["LightGoldenrod"]}}], ["font-lock-warning-face", {"true":{"bold":[true, "foreground", "Pink", "weight", "bold"]}}], ["fringe", {"true":{"background":["grey10"]}}], ["header-line", {"true":{"box":[{"line-width":-1, "style":"released-button"}, "background", "grey20", "foreground", "grey90", "box", null]}}], ["highlight", {"true":{"background":["darkolivegreen"]}}], ["info-header-node", {"true":{"italic":[true, "weight", "bold", "slant", "italic", "foreground", "white"]}}], ["info-header-xref", {"true":{"bold":[true, "weight", "bold", "foreground", "cyan"]}}], ["info-menu-5", {"true":{"foreground":["red1"]}}], ["info-menu-header", {"true":{"bold":[true, "family", "helv", "weight", "bold"]}}], ["info-node", {"true":{"italic":[true, "foreground", "white", "slant", "italic", "weight", "bold"]}}], ["info-xref", {"true":{"bold":[true, "foreground", "cyan", "weight", "bold"]}}], ["isearch", {"true":{"background":["palevioletred2", "foreground", "brown4"]}}], ["isearch-lazy-highlight-face", {"true":{"background":["paleturquoise4"]}}], ["italic", {"true":{"italic":[true, "slant", "italic"]}}], ["jde-bug-breakpoint-cursor", {"true":{"background":["brown", "foreground", "cyan"]}}], ["jde-db-active-breakpoint-face", {"true":{"background":["red", "foreground", "black"]}}], ["jde-db-requested-breakpoint-face", {"true":{"background":["yellow", "foreground", "black"]}}], ["jde-db-spec-breakpoint-face", {"true":{"background":["green", "foreground", "black"]}}], ["jde-java-font-lock-api-face", {"true":{"foreground":["light goldenrod"]}}], ["jde-java-font-lock-bold-face", {"true":{"bold":[true, "weight", "bold"]}}], ["jde-java-font-lock-code-face", {"true":{"null":null}}], ["jde-java-font-lock-constant-face", {"true":{"foreground":["Aquamarine"]}}], ["jde-java-font-lock-doc-tag-face", {"true":{"foreground":["light coral"]}}], ["jde-java-font-lock-italic-face", {"true":{"italic":[true, "slant", "italic"]}}], ["jde-java-font-lock-link-face", {"true":{"foreground":["blue", "underline", true, "slant", "normal"]}}], ["jde-java-font-lock-modifier-face", {"true":{"foreground":["LightSteelBlue"]}}], ["jde-java-font-lock-number-face", {"true":{"foreground":["LightSalmon"]}}], ["jde-java-font-lock-operator-face", {"true":{"foreground":["medium blue"]}}], ["jde-java-font-lock-package-face", {"true":{"foreground":["steelblue1"]}}], ["jde-java-font-lock-pre-face", {"true":{"null":null}}], ["jde-java-font-lock-underline-face", {"true":{"underline":[true]}}], ["menu", {"true":{"null":null}}], ["mode-line", {"true":{"background":["grey75", "foreground", "black", "box", {"line-width":-1, "style":"released-button"}]}}], ["mouse", {"true":{"background":["yellow"]}}], ["region", {"true":{"background":["blue3"]}}], ["scroll-bar", {"true":{"null":null}}], ["secondary-selection", {"true":{"background":["SkyBlue4"]}}], ["semantic-dirty-token-face", {"true":{"background":["gray10"]}}], ["semantic-unmatched-syntax-face", {"true":{"underline":["red"]}}], ["senator-intangible-face", {"true":{"foreground":["gray75"]}}], ["senator-momentary-highlight-face", {"true":{"background":["gray30"]}}], ["senator-read-only-face", {"true":{"background":["#664444"]}}], ["show-paren-match-face", {"true":{"background":["turquoise"]}}], ["show-paren-mismatch-face", {"true":{"background":["purple", "foreground", "white"]}}], ["speedbar-button-face", {"true":{"foreground":["green3"]}}], ["speedbar-directory-face", {"true":{"foreground":["light blue"]}}], ["speedbar-file-face", {"true":{"foreground":["cyan"]}}], ["speedbar-highlight-face", {"true":{"background":["sea green"]}}], ["speedbar-selected-face", {"true":{"foreground":["red", "underline", true]}}], ["speedbar-separator-face", {"true":{"background":["blue", "foreground", "white", "overline", "gray"]}}], ["speedbar-tag-face", {"true":{"foreground":["yellow"]}}], ["tool-bar", {"true":{"background":["grey75", "foreground", "black", "box", {"line-width":1, "style":"released-button"}]}}], ["trailing-whitespace", {"true":{"background":["red"]}}], ["underline", {"true":{"underline":[true]}}], ["variable-pitch", {"true":{"family":["helv"]}}], ["widget-button-face", {"true":{"bold":[true, "weight", "bold"]}}], ["widget-button-pressed-face", {"true":{"foreground":["red"]}}], ["widget-documentation-face", {"true":{"foreground":["lime green"]}}], ["widget-field-face", {"true":{"background":["dim gray"]}}], ["widget-inactive-face", {"true":{"foreground":["light gray"]}}], ["widget-single-line-field-face", {"true":{"background":["dim gray"]}}]]}