{"name": "color-theme-oswald","docs": ["Color theme by Tom Oswald, created 2001-04-18.", "Green on black, includes font-lock, show-paren, and ediff."],"data": ["color-theme-oswald", {"background-color":"black", "background-mode":"dark", "border-color":"black", "cursor-color":"black", "foreground-color":"green", "mouse-color":"black"}, {"blank-space-face":"blank-space-face", "blank-tab-face":"blank-tab-face", "list-matching-lines-face":"bold", "view-highlight-face":"highlight"}, ["default", {"true":{"null":null}}], ["blank-space-face", {"true":{"background":["LightGray"]}}], ["blank-tab-face", {"true":{"background":["green", "foreground", "black"]}}], ["bold", {"true":{"bold":[true]}}], ["bold-italic", {"true":{"italic":[true, "weight", "bold", "slant", "italic"]}}], ["ediff-current-diff-face-A", {"true":{"background":["pale green", "foreground", "firebrick"]}}], ["ediff-current-diff-face-Ancestor", {"true":{"background":["VioletRed", "foreground", "Black"]}}], ["ediff-current-diff-face-B", {"true":{"background":["Yellow", "foreground", "DarkOrchid"]}}], ["ediff-current-diff-face-C", {"true":{"background":["Pink", "foreground", "Navy"]}}], ["ediff-even-diff-face-A", {"true":{"background":["light grey", "foreground", "Black"]}}], ["ediff-even-diff-face-Ancestor", {"true":{"background":["Grey", "foreground", "White"]}}], ["ediff-even-diff-face-B", {"true":{"background":["Grey", "foreground", "White"]}}], ["ediff-even-diff-face-C", {"true":{"background":["light grey", "foreground", "Black"]}}], ["ediff-fine-diff-face-A", {"true":{"background":["sky blue", "foreground", "Navy"]}}], ["ediff-fine-diff-face-Ancestor", {"true":{"background":["Green", "foreground", "Black"]}}], ["ediff-fine-diff-face-B", {"true":{"background":["cyan", "foreground", "Black"]}}], ["ediff-fine-diff-face-C", {"true":{"background":["Turquoise", "foreground", "Black"]}}], ["ediff-odd-diff-face-A", {"true":{"background":["Grey", "foreground", "White"]}}], ["ediff-odd-diff-face-Ancestor", {"true":{"background":["light grey", "foreground", "Black"]}}], ["ediff-odd-diff-face-B", {"true":{"background":["light grey", "foreground", "Black"]}}], ["ediff-odd-diff-face-C", {"true":{"background":["Grey", "foreground", "White"]}}], ["font-lock-builtin-face", {"true":{"italic":[true, "foreground", "LightSteelBlue", "weight", "bold", "slant", "italic"]}}], ["font-lock-comment-face", {"true":{"italic":[true, "foreground", "LightGoldenrod4", "slant", "italic"]}}], ["font-lock-constant-face", {"true":{"italic":[true, "foreground", "HotPink", "slant", "italic"]}}], ["font-lock-doc-string-face", {"true":{"italic":[true, "foreground", "orange", "slant", "italic"]}}], ["font-lock-function-name-face", {"true":{"italic":[true, "foreground", "red", "weight", "bold", "slant", "italic"]}}], ["font-lock-keyword-face", {"true":{"foreground":["red"]}}], ["font-lock-preprocessor-face", {"true":{"italic":[true, "foreground", "HotPink", "slant", "italic"]}}], ["font-lock-string-face", {"true":{"italic":[true, "foreground", "orange", "slant", "italic"]}}], ["font-lock-reference-face", {"true":{"italic":[true, "foreground", "LightSteelBlue", "weight", "bold", "slant", "italic"]}}], ["font-lock-type-face", {"true":{"italic":[true, "foreground", "LightSlateBlue", "slant", "italic"]}}], ["font-lock-variable-name-face", {"true":{"underline":[true, "foreground", "LightGoldenrod"]}}], ["font-lock-warning-face", {"true":{"bold":[true, "foreground", "Pink", "weight", "bold"]}}], ["highlight", {"true":{"background":["yellow", "foreground", "red"]}}], ["isearch", {"true":{"background":["dim gray", "foreground", "aquamarine"]}}], ["ispell-face", {"true":{"bold":[true, "background", "#3454b4", "foreground", "yellow", "weight", "bold"]}}], ["italic", {"true":{"italic":[true]}}], ["modeline", {"true":{"background":["green", "foreground", "black"]}}], ["modeline-buffer-id", {"true":{"background":["green", "foreground", "black"]}}], ["modeline-mousable", {"true":{"background":["green", "foreground", "black"]}}], ["modeline-mousable-minor-mode", {"true":{"background":["green", "foreground", "black"]}}], ["region", {"true":{"background":["dim gray", "foreground", "aquamarine"]}}], ["secondary-selection", {"true":{"background":["darkslateblue", "foreground", "light goldenrod"]}}], ["show-paren-match-face", {"true":{"background":["turquoise", "foreground", "black"]}}], ["show-paren-mismatch-face", {"true":{"background":["purple", "foreground", "white"]}}], ["underline", {"true":{"underline":[true]}}], ["zmacs-region", {"true":{"background":["dim gray", "foreground", "aquamarine"]}}]]}